{
  "sections": [
    {
      "title": "hero",
      "content": "intro.md",
      "type": "text",
      "bgColor": "#194090"
    },
    {
      "title": "o que fazemos?",
      "type": "gallery",
      "content": "",
      "bgColor": "linear-gradient(to bottom, #194090 0%,#3c77cf 100%)",
      "cards": [
        {
          "image": "../images/gallery/mapeamento.png",
          "text": "card_mapeamento.md"
        },
        {
          "image": "../images/gallery/ideacao.png",
          "text": "card_ideacao.md"
        },
        {
          "image": "../images/gallery/projetos.png",
          "text": "card_projetos.md"
        }
      ]
    }
  ]
}
